{
  "name": "Sublime Text Preferences",
  "tagline": "My Sublime Text 3 preferences",
  "body": "# Sublime Text 3\r\n\r\n> The text editor you'll fall in love with\r\n\r\n> Sublime Text is a sophisticated text editor for code, markup and prose. You'll love the slick user interface, extraordinary features and amazing performance.\r\n\r\n* [Official website](http://www.sublimetext.com/3)\r\n* [Package Control](https://packagecontrol.io/)\r\n\r\n## Install\r\n\r\n### Sublime Text\r\n\r\n#### Windows\r\n\r\n- Download [installer](https://download.sublimetext.com/Sublime%20Text%20Build%203126%20x64%20Setup.exe) and run (check **Add to explorer context menu**)\r\n\r\n#### Linux Ubuntu (and Derivatives)\r\n\r\n```bash\r\nwget -c https://download.sublimetext.com/sublime-text_build-3126_amd64.deb\r\nsudo dpkg -i sublime-text*.deb\r\n```\r\n\r\n### Package Control\r\n\r\nFollow [this](https://packagecontrol.io/installation) instructions and close Sublime Text after installation\r\n\r\n### My Preferences\r\n\r\n#### Windows\r\n\r\n- Open **Command Prompt** by right-clicking and selecting **Run as Administrator**\r\n\r\n```powershell\r\ncd \"%appdata%/Sublime Text 3/Packages/\"\r\nmove User User-BKP\r\ngit clone https://github.com/magnobiet/sublime-text-preferences.git User\r\ncd User\r\nnpm run install\r\n```\r\n\r\n#### Linux Ubuntu (and Derivatives)\r\n\r\n```bash\r\ncd ~/.config/sublime-text-3/\r\nmv User User-BKP\r\ngit clone https://github.com/magnobiet/sublime-text-preferences.git User\r\n\r\ncd sublime-text-3\r\nsudo npm run install\r\n```\r\n\r\n## Installed Packages\r\n\r\n[Package Control.sublime-settings](https://github.com/magnobiet/sublime-text-preferences/blob/master/Package%20Control.sublime-settings#L6)\r\n\r\n## Icon\r\n\r\n![Sublime Text Icon](https://raw.githubusercontent.com/magnobiet/sublime-text/master/Icons/sublime-text.png)\r\n\r\nby [Jon-Paul Lunney](https://dribbble.com/shots/382465-Sublime-Text-2-update-Replacement-Icon)\r\n",
  "google": "",
  "note": "Don't delete this file! It's used internally to help with page regeneration."
}